{"batch": {"label": "batch", "average_duration": 0.13277237862348557, "n_events": 96, "total_time": 12.746148347854614}, "batch.accumulate": {"label": "batch.accumulate", "average_duration": 0.0009787215126885308, "n_events": 18, "total_time": 0.017616987228393555}, "batch.backward": {"label": "batch.backward", "average_duration": 0.06488628933827083, "n_events": 96, "total_time": 6.229083776473999}, "batch.evaluate": {"label": "batch.evaluate", "average_duration": 0.0012860000133514404, "n_events": 96, "total_time": 0.12345600128173828}, "batch.forward": {"label": "batch.forward", "average_duration": 0.006348416209220886, "n_events": 96, "total_time": 0.6094479560852051}, "batch.reduce": {"label": "batch.reduce", "average_duration": 0.2569547759162055, "n_events": 18, "total_time": 4.625185966491699}, "batch.step": {"label": "batch.step", "average_duration": 0.004061390956242879, "n_events": 96, "total_time": 0.3898935317993164}, "reduce.compress": {"label": "reduce.compress", "average_duration": 0.017108188735114202, "n_events": 18, "total_time": 0.30794739723205566}, "reduce.decompress": {"label": "reduce.decompress", "average_duration": 0.0009969472885131836, "n_events": 18, "total_time": 0.017945051193237305}, "reduce.flat_pack": {"label": "reduce.flat_pack", "average_duration": 0.0007592439651489258, "n_events": 18, "total_time": 0.013666391372680664}, "reduce.norm": {"label": "reduce.norm", "average_duration": 0.23484330707126194, "n_events": 18, "total_time": 4.227179527282715}, "reduce.setgrad": {"label": "reduce.setgrad", "average_duration": 0.0029370122485690648, "n_events": 18, "total_time": 0.052866220474243164}}