{"batch": {"label": "batch", "average_duration": 0.13178386836471953, "n_events": 193, "total_time": 25.43428659439087}, "batch.accumulate": {"label": "batch.accumulate", "average_duration": 0.0010292530059814453, "n_events": 18, "total_time": 0.018526554107666016}, "batch.backward": {"label": "batch.backward", "average_duration": 0.06514243387805366, "n_events": 193, "total_time": 12.572489738464355}, "batch.evaluate": {"label": "batch.evaluate", "average_duration": 0.0012159285767708418, "n_events": 193, "total_time": 0.23467421531677246}, "batch.forward": {"label": "batch.forward", "average_duration": 0.006377074384936397, "n_events": 193, "total_time": 1.2307753562927246}, "batch.reduce": {"label": "batch.reduce", "average_duration": 0.4742301305135091, "n_events": 18, "total_time": 8.536142349243164}, "batch.step": {"label": "batch.step", "average_duration": 0.004066011448598279, "n_events": 193, "total_time": 0.7847402095794678}, "epoch_metrics.collect": {"label": "epoch_metrics.collect", "average_duration": 0.22087979316711426, "n_events": 1, "total_time": 0.22087979316711426}, "reduce.compress": {"label": "reduce.compress", "average_duration": 0.0004304117626614041, "n_events": 18, "total_time": 0.0077474117279052734}, "reduce.decompress": {"label": "reduce.decompress", "average_duration": 9.201632605658637e-05, "n_events": 18, "total_time": 0.0016562938690185547}, "reduce.flat_pack": {"label": "reduce.flat_pack", "average_duration": 0.0008434322145250109, "n_events": 18, "total_time": 0.015181779861450195}, "reduce.norm": {"label": "reduce.norm", "average_duration": 0.4630062977472941, "n_events": 18, "total_time": 8.334113359451294}, "reduce.reduce.vector": {"label": "reduce.reduce.vector", "average_duration": 0.006211029158698188, "n_events": 18, "total_time": 0.11179852485656738}, "reduce.setgrad": {"label": "reduce.setgrad", "average_duration": 0.0030512412389119468, "n_events": 18, "total_time": 0.05492234230041504}, "test.last": {"label": "test.last", "average_duration": 1.8192033767700195, "n_events": 1, "total_time": 1.8192033767700195}}