{"batch": {"label": "batch", "average_duration": 0.0484321269166543, "n_events": 974, "total_time": 47.17289161682129}, "batch.accumulate": {"label": "batch.accumulate", "average_duration": 0.0010521399656605182, "n_events": 974, "total_time": 1.0247843265533447}, "batch.backward": {"label": "batch.backward", "average_duration": 0.007871440059105719, "n_events": 974, "total_time": 7.66678261756897}, "batch.evaluate": {"label": "batch.evaluate", "average_duration": 0.01828524268383363, "n_events": 974, "total_time": 17.809826374053955}, "batch.forward": {"label": "batch.forward", "average_duration": 0.004453731758149008, "n_events": 974, "total_time": 4.337934732437134}, "batch.reduce": {"label": "batch.reduce", "average_duration": 0.008457327280690782, "n_events": 974, "total_time": 8.237436771392822}, "batch.step": {"label": "batch.step", "average_duration": 0.005416550430673838, "n_events": 974, "total_time": 5.275720119476318}, "epoch_metrics.collect": {"label": "epoch_metrics.collect", "average_duration": 0.0012349486351013184, "n_events": 4, "total_time": 0.0049397945404052734}, "reduce.compress": {"label": "reduce.compress", "average_duration": 0.0003608144529056745, "n_events": 974, "total_time": 0.35143327713012695}, "reduce.decompress": {"label": "reduce.decompress", "average_duration": 7.617620472056175e-05, "n_events": 974, "total_time": 0.07419562339782715}, "reduce.flat_pack": {"label": "reduce.flat_pack", "average_duration": 0.0002917019493526012, "n_events": 974, "total_time": 0.2841176986694336}, "reduce.norm": {"label": "reduce.norm", "average_duration": 0.0036283004455253086, "n_events": 974, "total_time": 3.5339646339416504}, "reduce.reduce.vector": {"label": "reduce.reduce.vector", "average_duration": 0.00011953778825011831, "n_events": 974, "total_time": 0.11642980575561523}, "reduce.setgrad": {"label": "reduce.setgrad", "average_duration": 0.0033988259901011502, "n_events": 974, "total_time": 3.3104565143585205}, "test.last": {"label": "test.last", "average_duration": 0.9792198538780212, "n_events": 4, "total_time": 3.916879415512085}}